datacraft_geo/__init__.py
datacraft_geo/py.typed
datacraft_geo/suppliers.py
datacraft_geo-0.1.0.dist-info/LICENSE
datacraft_geo-0.1.0.dist-info/METADATA
datacraft_geo-0.1.0.dist-info/WHEEL
datacraft_geo-0.1.0.dist-info/entry_points.txt
datacraft_geo-0.1.0.dist-info/top_level.txt
datacraft_geo-0.1.0.dist-info/RECORD
