Metadata-Version: 2.1
Name: datacraft-geo
Version: 0.1.0
Summary: Custom geo type extensions for datacraft package
Home-page: https://github.com/bbux-dev/datacraft-geo
Author: Brian Buxton
Author-email: bbux-dev@gmail.com
License: MIT
License-File: LICENSE
Requires-Dist: datacraft (>=0.7.1)
Requires-Dist: mgrs
Requires-Dist: utm
Requires-Dist: shapely
Provides-Extra: all
Requires-Dist: pytest (>=6.2.2) ; extra == 'all'
Requires-Dist: pycodestyle ; extra == 'all'
Requires-Dist: pytest-cov ; extra == 'all'
Provides-Extra: test
Requires-Dist: pytest (>=6.2.2) ; extra == 'test'
Requires-Dist: pycodestyle ; extra == 'test'
Requires-Dist: pytest-cov ; extra == 'test'
